CalorIA/__init__.py
CalorIA/cli.py
CalorIA/seed.py
CalorIA/types.py
CalorIA/mixins/__init__.py
CalorIA/mixins/jwt_utils.py
CalorIA/mixins/mongo.py
CalorIA/mixins/tools.py
CalorIA/mixins/modules/__init__.py
CalorIA/mixins/modules/activities.py
CalorIA/mixins/modules/ai_assistant.py
CalorIA/mixins/modules/ingredients.py
CalorIA/mixins/modules/meal_prep.py
CalorIA/mixins/modules/meal_prep_assistants.py
CalorIA/mixins/modules/meals.py
CalorIA/mixins/modules/recipe_categories.py
CalorIA/mixins/modules/recipe_tags.py
CalorIA/mixins/modules/recipes.py
CalorIA/mixins/modules/users.py
CalorIA/mixins/modules/water.py
CalorIA/mixins/modules/weight.py
CalorIA/mixins/routes/__init__.py
CalorIA/mixins/routes/activity_routes.py
CalorIA/mixins/routes/ai_assistant_routes.py
CalorIA/mixins/routes/auth_routes.py
CalorIA/mixins/routes/dashboard_routes.py
CalorIA/mixins/routes/health_routes.py
CalorIA/mixins/routes/ingredient_routes.py
CalorIA/mixins/routes/meal_prep_routes.py
CalorIA/mixins/routes/meal_routes.py
CalorIA/mixins/routes/recipe_category_routes.py
CalorIA/mixins/routes/recipe_routes.py
CalorIA/mixins/routes/recipe_tag_routes.py
CalorIA/mixins/routes/trends_routes.py
CalorIA/mixins/routes/user_routes.py
CalorIA/mixins/routes/water_routes.py
CalorIA/mixins/routes/weight_routes.py
CalorIA/research/__init__.py
CalorIA/research/ingredients.py
CalorIA/research/recipes.py
CalorIA/research/tools.py
CalorIA/seed_db/ingredients.csv
CalorIA/seed_db/recipe_categories.csv
CalorIA/seed_db/recipe_tags.csv
CalorIA/seed_db/recipes.csv
caloria-1.0.0.dist-info/licenses/LICENSE
caloria-1.0.0.dist-info/METADATA
caloria-1.0.0.dist-info/WHEEL
caloria-1.0.0.dist-info/entry_points.txt
caloria-1.0.0.dist-info/top_level.txt
caloria-1.0.0.dist-info/RECORD
