Metadata-Version: 2.4
Name: caloria
Version: 1.0.0
Summary: A comprehensive full-stack calorie tracking application with Flask backend, React frontend, and AI-powered features
Home-page: https://github.com/jhd3197/CalorIA
Author: Juan Denis
Author-email: juan@vene.co
Project-URL: Bug Reports, https://github.com/yourusername/CalorIA/issues
Project-URL: Source, https://github.com/yourusername/CalorIA
Project-URL: Documentation, https://github.com/yourusername/CalorIA#readme
Keywords: caloria nutrition calories tracking flask react mongodb ai
Classifier: Development Status :: 4 - Beta
Classifier: Intended Audience :: Developers
Classifier: Intended Audience :: End Users/Desktop
Classifier: Topic :: Internet :: WWW/HTTP :: Dynamic Content
Classifier: Topic :: Scientific/Engineering :: Information Analysis
Classifier: License :: OSI Approved :: MIT License
Classifier: Programming Language :: Python :: 3
Classifier: Programming Language :: Python :: 3.7
Classifier: Programming Language :: Python :: 3.8
Classifier: Programming Language :: Python :: 3.9
Classifier: Programming Language :: Python :: 3.10
Classifier: Programming Language :: Python :: 3.11
Classifier: Operating System :: OS Independent
Classifier: Framework :: Flask
Requires-Python: >=3.7
License-File: LICENSE
Requires-Dist: Flask==2.3.3
Requires-Dist: pymongo[srv]==4.6.0
Requires-Dist: python-dotenv==1.0.0
Requires-Dist: Flask-Cors==4.0.0
Requires-Dist: click==8.1.7
Requires-Dist: pydantic==2.5.0
Requires-Dist: Werkzeug==2.3.7
Requires-Dist: PyJWT==2.8.0
Requires-Dist: openai==0.28.0
Requires-Dist: requests==2.31.0
Requires-Dist: python-slugify
Dynamic: author
Dynamic: author-email
Dynamic: classifier
Dynamic: description
Dynamic: description-content-type
Dynamic: home-page
Dynamic: keywords
Dynamic: license-file
Dynamic: project-url
Dynamic: requires-dist
Dynamic: requires-python
Dynamic: summary
